slicks/__init__.py
slicks/battery.py
slicks/calculations.py
slicks/config.py
slicks/discovery.py
slicks/fetcher.py
slicks/movement_detector.py
slicks-0.1.2.dist-info/METADATA
slicks-0.1.2.dist-info/WHEEL
slicks-0.1.2.dist-info/top_level.txt
slicks-0.1.2.dist-info/RECORD
