Metadata-Version: 2.4
Name: slicks
Version: 0.1.2
Summary: The home baked data pipeline for Western Formula Racing
Author-email: Western Formula Racing <fsae.uwo@gmail.com>
Project-URL: Homepage, https://github.com/Western-Formula-Racing/wfr-telemetry
Project-URL: Documentation, https://western-formula-racing.github.io/wfr-telemetry/
Project-URL: Bug Tracker, https://github.com/Western-Formula-Racing/wfr-telemetry/issues
Classifier: Programming Language :: Python :: 3
Classifier: License :: OSI Approved :: MIT License
Classifier: Operating System :: OS Independent
Requires-Python: >=3.11
Requires-Dist: pandas>=2.0.0
Requires-Dist: influxdb3-python>=0.1.0
Requires-Dist: python-dotenv>=1.0.0
Requires-Dist: matplotlib>=3.0.0
